<?xml version="1.0" encoding="UTF-8"?>
<java version="20.0.2" class="java.beans.XMLDecoder">
 <object class="src.Game" id="Game0">
  <void property="lastId">
   <string>B0AA0</string>
  </void>
  <void property="loggedUser">
   <object class="src.users.Admin" id="Admin0">
    <void property="name">
     <string>a</string>
    </void>
    <void property="nick">
     <string>a</string>
    </void>
    <void property="password">
     <string>a</string>
    </void>
   </object>
  </void>
  <void property="users">
   <void method="add">
    <object class="src.users.Player">
     <void property="gold">
      <int>500</int>
     </void>
     <void property="id">
      <string>A0AA0</string>
     </void>
     <void property="name">
      <string>2</string>
     </void>
     <void property="nick">
      <string>2</string>
     </void>
     <void property="password">
      <string>2</string>
     </void>
    </object>
   </void>
   <void method="add">
    <object class="src.users.Player">
     <void property="gold">
      <int>500</int>
     </void>
     <void property="id">
      <string>A0AA1</string>
     </void>
     <void property="name">
      <string>1</string>
     </void>
     <void property="nick">
      <string>1</string>
     </void>
     <void property="password">
      <string>1</string>
     </void>
    </object>
   </void>
   <void method="add">
    <object class="src.users.Player">
     <void property="gold">
      <int>500</int>
     </void>
     <void property="id">
      <string>B0AA0</string>
     </void>
     <void property="name">
      <string>5</string>
     </void>
     <void property="nick">
      <string>5</string>
     </void>
     <void property="password">
      <string>5</string>
     </void>
    </object>
   </void>
   <void method="add">
    <object idref="Admin0"/>
   </void>
  </void>
 </object>
</java>
